japanese_addresses/__init__.py
japanese_addresses/prefecture2city2street.pkl
japanese_addresses/VERSION.py
japanese_addresses-0.0.3.dist-info/LICENSE
japanese_addresses-0.0.3.dist-info/WHEEL
japanese_addresses-0.0.3.dist-info/METADATA
japanese_addresses-0.0.3.dist-info/RECORD
