Metadata-Version: 2.1
Name: japanese-addresses
Version: 0.0.3
Summary: 
Home-page: https://github.com/wakamezake/japanese-addresses.git
License: MIT
Author: wakame
Author-email: hotwater1367@gmail.com
Requires-Python: >=3.6.1,<4.0.0
Classifier: License :: OSI Approved :: MIT License
Classifier: Programming Language :: Python :: 3
Classifier: Programming Language :: Python :: 3.7
Classifier: Programming Language :: Python :: 3.8
Requires-Dist: dataclasses (>=0.7,<0.8); python_version >= "3.6" and python_version < "3.7"
Requires-Dist: kanjize (>=0.1.0,<0.2.0)
Project-URL: Repository, https://github.com/wakamezake/japanese-addresses.git
